VizXpress/__init__.py
VizXpress/bar.py
VizXpress/dendrogram.py
VizXpress/density.py
VizXpress/dott_plot.py
VizXpress/gsea.py
VizXpress/heatmap.py
VizXpress/helpers.py
VizXpress/kmeans.py
VizXpress/misc.py
VizXpress/pca.py
VizXpress/plot_pca.py
VizXpress/plotly.py
VizXpress/ridge_plot.py
VizXpress/venn.py
VizXpress/violin.py
VizXpress/volcano.py
vizxpress-0.0.2.1.dist-info/METADATA
vizxpress-0.0.2.1.dist-info/WHEEL
vizxpress-0.0.2.1.dist-info/top_level.txt
vizxpress-0.0.2.1.dist-info/RECORD
