Metadata-Version: 2.1
Name: vizxpress
Version: 0.0.2.1
Summary: A unified set of analysis and visualization tools intended for gene expression studies in Python
Home-page: UNKNOWN
Author: Colton J. Garelli
Author-email: 
License: GNU Affero General Public License v3.0
Platform: UNKNOWN
Requires-Python: >=3.6
